assigner/canvas.py
assigner/roster_util.py
assigner/__init__.py
assigner/exceptions.py
assigner/config.py
assigner/progress.py
assigner/baserepo.py
assigner/commands/canvas.py
assigner/commands/commit.py
assigner/commands/new.py
assigner/commands/__init__.py
assigner/commands/score.py
assigner/commands/unarchive.py
assigner/commands/archive.py
assigner/commands/unlock.py
assigner/commands/open.py
assigner/commands/import.py
assigner/commands/protect.py
assigner/commands/unprotect.py
assigner/commands/assign.py
assigner/commands/status.py
assigner/commands/set.py
assigner/commands/lock.py
assigner/commands/roster.py
assigner/commands/init.py
assigner/commands/get.py
assigner/commands/push.py
assigner/backends/__init__.py
assigner/backends/exceptions.py
assigner/backends/mock.py
assigner/backends/git_exceptions.py
assigner/backends/base.py
assigner/backends/gitlab_exceptions.py
assigner/backends/decorators.py
assigner/backends/gitlab.py
assigner/config/__init__.py
assigner/config/upgrades.py
assigner/config/versions.py
assigner/config/schemas/v1.py
assigner/config/schemas/v3.py
assigner/config/schemas/__init__.py
assigner/config/schemas/v2.py
assigner/config/schemas/v0.py
assigner/tests/__init__.py
assigner/tests/utils.py
assigner/tests/assigner_test.py
assigner/tests/config_test.py
assigner/tests/commands/get_integration_test.py
assigner/tests/commands/__init__.py
assigner/tests/commands/help_integration_test.py
assigner-3.1.2.dist-info/entry_points.txt
assigner-3.1.2.dist-info/RECORD
assigner-3.1.2.dist-info/METADATA
assigner-3.1.2.dist-info/top_level.txt
assigner-3.1.2.dist-info/WHEEL
assigner-3.1.2.dist-info/metadata.json
assigner-3.1.2.dist-info/DESCRIPTION.rst
assigner-3.1.2.data/data/share/assigner/TUTORIAL.md
assigner-3.1.2.data/data/share/assigner/_config.example.yml
