Metadata-Version: 2.0
Name: assigner
Version: 3.1.2
Summary: Automatically assign programming homework to students on GitLab
Home-page: https://github.com/redkyn/assigner
Author: N. Jarus, M. Wisely, & T. Morrow
Author-email: jarus@mst.edu
License: UNKNOWN
Platform: UNKNOWN
Classifier: Development Status :: 5 - Production/Stable
Classifier: Intended Audience :: Education
Classifier: Topic :: Education
Classifier: Topic :: Software Development :: Version Control :: Git
Classifier: Environment :: Console
Classifier: License :: OSI Approved :: MIT License
Classifier: Programming Language :: Python :: 3
Classifier: Programming Language :: Python :: 3 :: Only
Classifier: Programming Language :: Python :: 3.4
Classifier: Programming Language :: Python :: 3.5
Classifier: Programming Language :: Python :: 3.6
Classifier: Programming Language :: Python :: 3.7
Classifier: Programming Language :: Python :: 3.8
Classifier: Programming Language :: Python :: 3.9
Requires-Python: >=3.4
Requires-Dist: GitPython (>=2.1.8)
Requires-Dist: PTable (>=0.9)
Requires-Dist: PyYAML (>=3.13)
Requires-Dist: colorlog (<3,>=2.6)
Requires-Dist: enlighten (>=1.5.0)
Requires-Dist: jsonschema (>=2.5)
Requires-Dist: redkyn-common (>=1.1.0)
Requires-Dist: requests (>=2.20.0)
